bfsk_project/bfsk_modulator.v
// =============================================================
// Module   : bfsk_modulator.v
// Function : Binary FSK Modulator — flat RTL version
//            All logic in a single always block.
//            Synthesizable, FPGA/ASIC ready.
//
// Operation:
//   Generates a square-wave output that toggles at frequency
//   f1 when data_in='1', or f0 when data_in='0'.
//
// Parameters:
//   F0_DIV  - Divisor for space frequency f0  (bit '0')
//   F1_DIV  - Divisor for mark  frequency f1  (bit '1')
//
// Frequency formula:
//   f_out = f_clk / (2 x FDIV)
//
// Example (50 MHz clock):
//   F0_DIV = 50  ->  f0 = 500 kHz
//   F1_DIV = 25  ->  f1 = 1 MHz
// =============================================================

module bfsk_modulator (
    input  wire clk,            // Master system clock
    input  wire rst,            // Synchronous active-high reset
    input  wire data_in,        // Serial binary data input
    output reg  modulated_out   // BFSK modulated square-wave output
);

    parameter F0_DIV = 8'd50;   // Space frequency divisor (bit '0')
    parameter F1_DIV = 8'd25;   // Mark  frequency divisor (bit '1')

    // ── Internal counter ───────────────────────────────────────
    reg [7:0] counter;

    // ── Sequential logic ───────────────────────────────────────
    always @(posedge clk) begin
        if (rst) begin
            counter       <= 8'd0;
            modulated_out <= 1'b0;

        end else begin

            if (data_in == 1'b1) begin
                // ── Mark frequency  f1 ───────────────────────
                if (counter >= F1_DIV - 8'd1) begin
                    counter       <= 8'd0;
                    modulated_out <= ~modulated_out;
                end else begin
                    counter <= counter + 8'd1;
                end

            end else begin
                // ── Space frequency f0 ───────────────────────
                if (counter >= F0_DIV - 8'd1) begin
                    counter       <= 8'd0;
                    modulated_out <= ~modulated_out;
                end else begin
                    counter <= counter + 8'd1;
                end
            end

        end
    end

endmodule

bfsk_project/data_input_module.v
// =============================================================
// Module   : data_input_module.v
// Function : Parallel-to-Serial Data Input Module
//            Accepts an 8-bit parallel byte, serialises it
//            MSB-first at a configurable bit rate, and drives
//            the serial_out line for the BFSK modulator.
//
// Inputs:
//   clk           - System clock
//   rst           - Synchronous active-high reset
//   parallel_data - 8-bit data byte to transmit
//   load          - Active-high 1-cycle load/start pulse
//   bit_period    - Number of clock cycles per bit
//                   (e.g. 2500 @ 50 MHz = 50 µs/bit = 20 kbps)
//
// Outputs:
//   serial_out    - MSB-first serial data stream
//   tx_busy       - High while transmitting
//   tx_done       - 1-cycle high pulse when all 8 bits sent
//
// State machine:
//   IDLE  -> TRANSMIT (on load) -> IDLE (after 8 bits)
// =============================================================

module data_input_module (
    input  wire        clk,
    input  wire        rst,
    input  wire [7:0]  parallel_data,
    input  wire        load,
    input  wire [15:0] bit_period,
    output reg         serial_out,
    output reg         tx_busy,
    output reg         tx_done
);

    // ── State encoding ─────────────────────────────────────────
    localparam IDLE     = 1'b0;
    localparam TRANSMIT = 1'b1;

    // ── Internal registers ─────────────────────────────────────
    reg        state;
    reg [7:0]  shift_reg;       // Shift register holding current byte
    reg [15:0] bit_timer;       // Counts clk cycles within one bit period
    reg [3:0]  bit_index;       // Which bit we are currently sending (0=MSB)

    // ── Sequential logic ───────────────────────────────────────
    always @(posedge clk) begin
        if (rst) begin
            state      <= IDLE;
            shift_reg  <= 8'd0;
            bit_timer  <= 16'd0;
            bit_index  <= 4'd0;
            serial_out <= 1'b0;
            tx_busy    <= 1'b0;
            tx_done    <= 1'b0;
        end else begin

            // Default: clear single-cycle signals
            tx_done <= 1'b0;

            case (state)

                // ── IDLE ─────────────────────────────────────
                IDLE: begin
                    serial_out <= 1'b0;
                    tx_busy    <= 1'b0;

                    if (load) begin
                        shift_reg  <= parallel_data;          // Latch input
                        serial_out <= parallel_data[7];       // Output MSB immediately
                        bit_timer  <= 16'd0;
                        bit_index  <= 4'd0;
                        tx_busy    <= 1'b1;
                        state      <= TRANSMIT;
                    end
                end

                // ── TRANSMIT ─────────────────────────────────
                TRANSMIT: begin
                    if (bit_timer >= bit_period - 1) begin
                        // Current bit period expired — advance to next bit
                        bit_timer <= 16'd0;

                        if (bit_index == 4'd7) begin
                            // All 8 bits sent → return to IDLE
                            state      <= IDLE;
                            tx_busy    <= 1'b0;
                            tx_done    <= 1'b1;
                            serial_out <= 1'b0;
                            bit_index  <= 4'd0;
                        end else begin
                            // Shift left and output next bit
                            shift_reg  <= {shift_reg[6:0], 1'b0};
                            serial_out <= shift_reg[6];   // Uses old value (non-blocking)
                            bit_index  <= bit_index + 4'd1;
                        end

                    end else begin
                        // Still within current bit period — hold output
                        bit_timer <= bit_timer + 16'd1;
                    end
                end

                default: state <= IDLE;
            endcase
        end
    end

endmodule

bfsk_project/bfsk_top.v
// =============================================================
// Module   : bfsk_top.v
// Function : Top-Level Integration Module
//            Connects the Data Input Module (parallel->serial)
//            with the BFSK Modulator.
//
//            ┌─────────────────────────────────────────────────┐
//            │               bfsk_top                          │
//            │                                                 │
//  clk  ─────┤──►  data_input_module  ──serial──►  bfsk_mod ──┤──► modulated_out
//  rst  ─────┤                                                 │
//  data ─────┤   (8-bit parallel in)   (1-bit serial)         │
//  load ─────┤                                                 │
//            └─────────────────────────────────────────────────┘
//
// Parameters:
//   F0_DIV     - Space frequency divisor (default 50  -> 500 kHz @ 50 MHz)
//   F1_DIV     - Mark  frequency divisor (default 25  -> 1 MHz   @ 50 MHz)
//   BIT_PERIOD - Clock cycles per bit    (default 2500 -> 20 kbps @ 50 MHz)
// =============================================================


module bfsk_top (
    input  wire        clk,            // Master clock (50 MHz)
    input  wire        rst,            // Synchronous active-high reset
    input  wire [7:0]  parallel_data,  // 8-bit byte to transmit
    input  wire        load,           // Pulse high to start transmission
    output wire        modulated_out,  // BFSK modulated output
    output wire        tx_busy,        // High during transmission
    output wire        tx_done         // 1-cycle pulse when byte is sent
);

    parameter F0_DIV     = 8'd50;        // Space divisor  (bit '0')
    parameter F1_DIV     = 8'd25;        // Mark  divisor  (bit '1')
    parameter BIT_PERIOD = 16'd2500;     // Clk cycles per bit

    // ── Internal wire: serial data from DIM to modulator ───────
    wire serial_data;

    // ── Block 1 : Data Input Module (Parallel-to-Serial) ───────
    data_input_module u_dim (
        .clk           (clk),
        .rst           (rst),
        .parallel_data (parallel_data),
        .load          (load),
        .bit_period    (BIT_PERIOD),
        .serial_out    (serial_data),
        .tx_busy       (tx_busy),
        .tx_done       (tx_done)
    );

    // ── Block 2 : BFSK Modulator ────────────────────────────────
    bfsk_modulator #(
        .F0_DIV (F0_DIV),
        .F1_DIV (F1_DIV)
    ) u_mod (
        .clk           (clk),
        .rst           (rst),
        .data_in       (serial_data),
        .modulated_out (modulated_out)
    );

endmodule

bfsk_project/bfsk_top_tb.v
// =============================================================
// Module   : bfsk_top_tb.v
// Function : Testbench for bfsk_top (full system)
//            Sends multiple 8-bit bytes through the
//            data_input_module and verifies BFSK modulation.
//
// Test bytes:
//   Byte 1: 0xA5 = 1010_0101  (alternating 1s and 0s)
//   Byte 2: 0xFF = 1111_1111  (all mark frequency)
//   Byte 3: 0x00 = 0000_0000  (all space frequency)
//   Byte 4: 0xB6 = 1011_0110  (mixed pattern)
//
// BIT_PERIOD = 100 cycles (shortened for simulation speed)
//   @ 50 MHz -> 2 µs per bit (500 kbps)
// =============================================================

`timescale 1ns / 1ps

module bfsk_top_tb;

    // ── DUT signal declarations ────────────────────────────────
    reg         clk;
    reg         rst;
    reg  [7:0]  parallel_data;
    reg         load;
    wire        modulated_out;
    wire        tx_busy;
    wire        tx_done;

    // ── DUT instantiation ──────────────────────────────────────
    // Use BIT_PERIOD=100 for faster simulation
    bfsk_top #(
        .F0_DIV     (8'd50),
        .F1_DIV     (8'd25),
        .BIT_PERIOD (16'd100)
    ) u_dut (
        .clk           (clk),
        .rst           (rst),
        .parallel_data (parallel_data),
        .load          (load),
        .modulated_out (modulated_out),
        .tx_busy       (tx_busy),
        .tx_done       (tx_done)
    );

    // ── Clock: 50 MHz, period = 20 ns ──────────────────────────
    initial  clk = 1'b0;
    always   #10 clk = ~clk;

    // ── VCD waveform dump ──────────────────────────────────────
    initial begin
        $dumpfile("bfsk_top.vcd");
        $dumpvars(0, bfsk_top_tb);
    end

    // ── Console monitor ────────────────────────────────────────
    initial begin
        $monitor("TIME=%0t ns | load=%b | busy=%b | done=%b | out=%b",
                 $time, load, tx_busy, tx_done, modulated_out);
    end

    // ── Task: send one byte and wait for completion ─────────────
    task send_byte;
        input [7:0] byte_val;
        begin
            $display("\n--- Sending byte: 0x%02X (%08b) ---", byte_val, byte_val);
            @(negedge clk);         // Align to negedge for safe setup
            parallel_data = byte_val;
            load          = 1'b1;
            @(posedge clk);         // Load latches on this edge
            @(negedge clk);
            load          = 1'b0;

            // Wait for transmission complete
            @(posedge tx_done);
            $display("--- Byte 0x%02X transmission done at t=%0t ns ---", byte_val, $time);
            #200;                   // Small gap between bytes
        end
    endtask

    // ── Test stimulus ──────────────────────────────────────────
    initial begin
        $display("========================================");
        $display("  BFSK Top-Level Testbench Start");
        $display("  F0_DIV=50 F1_DIV=25 BIT_PERIOD=100");
        $display("========================================");

        // 1) Initialise
        rst           = 1'b1;
        load          = 1'b0;
        parallel_data = 8'h00;
        @(posedge clk);
        @(posedge clk);
        rst = 1'b0;
        #50;

        // 2) Send four different bytes
        send_byte(8'hA5);   // 1010_0101
        send_byte(8'hFF);   // 1111_1111  (all mark)
        send_byte(8'h00);   // 0000_0000  (all space)
        send_byte(8'hB6);   // 1011_0110

        // 3) Test reset during active transmission
        $display("\n--- Testing mid-transmission reset ---");
        parallel_data = 8'h55;
        load          = 1'b1;
        @(posedge clk);
        load = 1'b0;
        #500;                   // Wait partway through
        rst  = 1'b1;
        @(posedge clk);
        rst  = 1'b0;
        $display("    Reset asserted and deasserted.");
        #200;

        // 4) Resume normal operation after reset
        send_byte(8'hCC);   // 1100_1100

        $display("\n========================================");
        $display("  BFSK Top-Level Testbench Complete");
        $display("========================================");
        $finish;
    end

endmodule

bfsk_project/bfsk_top.vcd
$date
	Wed Jun 10 05:36:59 2026
$end
$version
	Icarus Verilog
$end
$timescale
	1ps
$end
$scope module bfsk_top_tb $end
$var wire 1 ! tx_done $end
$var wire 1 " tx_busy $end
$var wire 1 # modulated_out $end
$var reg 1 $ clk $end
$var reg 1 % load $end
$var reg 8 & parallel_data [7:0] $end
$var reg 1 ' rst $end
$scope module u_dut $end
$var wire 1 $ clk $end
$var wire 1 % load $end
$var wire 8 ( parallel_data [7:0] $end
$var wire 1 ' rst $end
$var wire 1 ! tx_done $end
$var wire 1 " tx_busy $end
$var wire 1 ) serial_data $end
$var wire 1 # modulated_out $end
$var parameter 16 * BIT_PERIOD $end
$var parameter 8 + F0_DIV $end
$var parameter 8 , F1_DIV $end
$scope module u_dim $end
$var wire 16 - bit_period [15:0] $end
$var wire 1 $ clk $end
$var wire 1 % load $end
$var wire 8 . parallel_data [7:0] $end
$var wire 1 ' rst $end
$var parameter 1 / IDLE $end
$var parameter 1 0 TRANSMIT $end
$var reg 4 1 bit_index [3:0] $end
$var reg 16 2 bit_timer [15:0] $end
$var reg 1 ) serial_out $end
$var reg 8 3 shift_reg [7:0] $end
$var reg 1 4 state $end
$var reg 1 " tx_busy $end
$var reg 1 ! tx_done $end
$upscope $end
$scope module u_mod $end
$var wire 1 $ clk $end
$var wire 1 ) data_in $end
$var wire 1 ' rst $end
$var parameter 8 5 F0_DIV $end
$var parameter 8 6 F1_DIV $end
$var reg 8 7 counter [7:0] $end
$var reg 1 # modulated_out $end
$upscope $end
$upscope $end
$scope task send_byte $end
$var reg 8 8 byte_val [7:0] $end
$upscope $end
$upscope $end
$enddefinitions $end
$comment Show the parameter values. $end
$dumpall
b11001 6
b110010 5
10
0/
b11001 ,
b110010 +
b1100100 *
$end
#0
$dumpvars
bx 8
bx 7
x4
bx 3
bx 2
bx 1
b0 .
b1100100 -
x)
b0 (
1'
b0 &
0%
0$
x#
x"
x!
$end
#10000
0!
0"
0)
b0 1
b0 2
b0 3
04
0#
b0 7
1$
#20000
0$
#30000
0'
1$
#40000
0$
#50000
b1 7
1$
#60000
0$
#70000
b10 7
1$
#80000
1%
b10100101 &
b10100101 (
b10100101 .
0$
b10100101 8
#90000
14
1"
1)
b10100101 3
b11 7
1$
#100000
0%
0$
#110000
b100 7
b1 2
1$
#120000
0$
#130000
b10 2
b101 7
1$
#140000
0$
#150000
b110 7
b11 2
1$
#160000
0$
#170000
b100 2
b111 7
1$
#180000
0$
#190000
b1000 7
b101 2
1$
#200000
0$
#210000
b110 2
b1001 7
1$
#220000
0$
#230000
b1010 7
b111 2
1$
#240000
0$
#250000
b1000 2
b1011 7
1$
#260000
0$
#270000
b1100 7
b1001 2
1$
#280000
0$
#290000
b1010 2
b1101 7
1$
#300000
0$
#310000
b1110 7
b1011 2
1$
#320000
0$
#330000
b1100 2
b1111 7
1$
#340000
0$
#350000
b10000 7
b1101 2
1$
#360000
0$
#370000
b1110 2
b10001 7
1$
#380000
0$
#390000
b10010 7
b1111 2
1$
#400000
0$
#410000
b10000 2
b10011 7
1$
#420000
0$
#430000
b10100 7
b10001 2
1$
#440000
0$
#450000
b10010 2
b10101 7
1$
#460000
0$
#470000
b10110 7
b10011 2
1$
#480000
0$
#490000
b10100 2
b10111 7
1$
#500000
0$
#510000
b11000 7
b10101 2
1$
#520000
0$
#530000
b10110 2
1#
b0 7
1$
#540000
0$
#550000
b1 7
b10111 2
1$
#560000
0$
#570000
b11000 2
b10 7
1$
#580000
0$
#590000
b11 7
b11001 2
1$
#600000
0$
#610000
b11010 2
b100 7
1$
#620000
0$
#630000
b101 7
b11011 2
1$
#640000
0$
#650000
b11100 2
b110 7
1$
#660000
0$
#670000
b111 7
b11101 2
1$
#680000
0$
#690000
b11110 2
b1000 7
1$
#700000
0$
#710000
b1001 7
b11111 2
1$
#720000
0$
#730000
b100000 2
b1010 7
1$
#740000
0$
#750000
b1011 7
b100001 2
1$
#760000
0$
#770000
b100010 2
b1100 7
1$
#780000
0$
#790000
b1101 7
b100011 2
1$
#800000
0$
#810000
b100100 2
b1110 7
1$
#820000
0$
#830000
b1111 7
b100101 2
1$
#840000
0$
#850000
b100110 2
b10000 7
1$
#860000
0$
#870000
b10001 7
b100111 2
1$
#880000
0$
#890000
b101000 2
b10010 7
1$
#900000
0$
#910000
b10011 7
b101001 2
1$
#920000
0$
#930000
b101010 2
b10100 7
1$
#940000
0$
#950000
b10101 7
b101011 2
1$
#960000
0$
#970000
b101100 2
b10110 7
1$
#980000
0$
#990000
b10111 7
b101101 2
1$
#1000000
0$
#1010000
b101110 2
b11000 7
1$
#1020000
0$
#1030000
0#
b0 7
b101111 2
1$
#1040000
0$
#1050000
b110000 2
b1 7
1$
#1060000
0$
#1070000
b10 7
b110001 2
1$
#1080000
0$
#1090000
b110010 2
b11 7
1$
#1100000
0$
#1110000
b100 7
b110011 2
1$
#1120000
0$
#1130000
b110100 2
b101 7
1$
#1140000
0$
#1150000
b110 7
b110101 2
1$
#1160000
0$
#1170000
b110110 2
b111 7
1$
#1180000
0$
#1190000
b1000 7
b110111 2
1$
#1200000
0$
#1210000
b111000 2
b1001 7
1$
#1220000
0$
#1230000
b1010 7
b111001 2
1$
#1240000
0$
#1250000
b111010 2
b1011 7
1$
#1260000
0$
#1270000
b1100 7
b111011 2
1$
#1280000
0$
#1290000
b111100 2
b1101 7
1$
#1300000
0$
#1310000
b1110 7
b111101 2
1$
#1320000
0$
#1330000
b111110 2
b1111 7
1$
#1340000
0$
#1350000
b10000 7
b111111 2
1$
#1360000
0$
#1370000
b1000000 2
b10001 7
1$
#1380000
0$
#1390000
b10010 7
b1000001 2
1$
#1400000
0$
#1410000
b1000010 2
b10011 7
1$
#1420000
0$
#1430000
b10100 7
b1000011 2
1$
#1440000
0$
#1450000
b1000100 2
b10101 7
1$
#1460000
0$
#1470000
b10110 7
b1000101 2
1$
#1480000
0$
#1490000
b1000110 2
b10111 7
1$
#1500000
0$
#1510000
b11000 7
b1000111 2
1$
#1520000
0$
#1530000
b1001000 2
1#
b0 7
1$
#1540000
0$
#1550000
b1 7
b1001001 2
1$
#1560000
0$
#1570000
b1001010 2
b10 7
1$
#1580000
0$
#1590000
b11 7
b1001011 2
1$
#1600000
0$
#1610000
b1001100 2
b100 7
1$
#1620000
0$
#1630000
b101 7
b1001101 2
1$
#1640000
0$
#1650000
b1001110 2
b110 7
1$
#1660000
0$
#1670000
b111 7
b1001111 2
1$
#1680000
0$
#1690000
b1010000 2
b1000 7
1$
#1700000
0$
#1710000
b1001 7
b1010001 2
1$
#1720000
0$
#1730000
b1010010 2
b1010 7
1$
#1740000
0$
#1750000
b1011 7
b1010011 2
1$
#1760000
0$
#1770000
b1010100 2
b1100 7
1$
#1780000
0$
#1790000
b1101 7
b1010101 2
1$
#1800000
0$
#1810000
b1010110 2
b1110 7
1$
#1820000
0$
#1830000
b1111 7
b1010111 2
1$
#1840000
0$
#1850000
b1011000 2
b10000 7
1$
#1860000
0$
#1870000
b10001 7
b1011001 2
1$
#1880000
0$
#1890000
b1011010 2
b10010 7
1$
#1900000
0$
#1910000
b10011 7
b1011011 2
1$
#1920000
0$
#1930000
b1011100 2
b10100 7
1$
#1940000
0$
#1950000
b10101 7
b1011101 2
1$
#1960000
0$
#1970000
b1011110 2
b10110 7
1$
#1980000
0$
#1990000
b10111 7
b1011111 2
1$
#2000000
0$
#2010000
b1100000 2
b11000 7
1$
#2020000
0$
#2030000
0#
b0 7
b1100001 2
1$
#2040000
0$
#2050000
b1100010 2
b1 7
1$
#2060000
0$
#2070000
b10 7
b1100011 2
1$
#2080000
0$
#2090000
b1 1
0)
b1001010 3
b0 2
b11 7
1$
#2100000
0$
#2110000
b100 7
b1 2
1$
#2120000
0$
#2130000
b10 2
b101 7
1$
#2140000
0$
#2150000
b110 7
b11 2
1$
#2160000
0$
#2170000
b100 2
b111 7
1$
#2180000
0$
#2190000
b1000 7
b101 2
1$
#2200000
0$
#2210000
b110 2
b1001 7
1$
#2220000
0$
#2230000
b1010 7
b111 2
1$
#2240000
0$
#2250000
b1000 2
b1011 7
1$
#2260000
0$
#2270000
b1100 7
b1001 2
1$
#2280000
0$
#2290000
b1010 2
b1101 7
1$
#2300000
0$
#2310000
b1110 7
b1011 2
1$
#2320000
0$
#2330000
b1100 2
b1111 7
1$
#2340000
0$
#2350000
b10000 7
b1101 2
1$
#2360000
0$
#2370000
b1110 2
b10001 7
1$
#2380000
0$
#2390000
b10010 7
b1111 2
1$
#2400000
0$
#2410000
b10000 2
b10011 7
1$
#2420000
0$
#2430000
b10100 7
b10001 2
1$
#2440000
0$
#2450000
b10010 2
b10101 7
1$
#2460000
0$
#2470000
b10110 7
b10011 2
1$
#2480000
0$
#2490000
b10100 2
b10111 7
1$
#2500000
0$
#2510000
b11000 7
b10101 2
1$
#2520000
0$
#2530000
b10110 2
b11001 7
1$
#2540000
0$
#2550000
b11010 7
b10111 2
1$
#2560000
0$
#2570000
b11000 2
b11011 7
1$
#2580000
0$
#2590000
b11100 7
b11001 2
1$
#2600000
0$
#2610000
b11010 2
b11101 7
1$
#2620000
0$
#2630000
b11110 7
b11011 2
1$
#2640000
0$
#2650000
b11100 2
b11111 7
1$
#2660000
0$
#2670000
b100000 7
b11101 2
1$
#2680000
0$
#2690000
b11110 2
b100001 7
1$
#2700000
0$
#2710000
b100010 7
b11111 2
1$
#2720000
0$
#2730000
b100000 2
b100011 7
1$
#2740000
0$
#2750000
b100100 7
b100001 2
1$
#2760000
0$
#2770000
b100010 2
b100101 7
1$
#2780000
0$
#2790000
b100110 7
b100011 2
1$
#2800000
0$
#2810000
b100100 2
b100111 7
1$
#2820000
0$
#2830000
b101000 7
b100101 2
1$
#2840000
0$
#2850000
b100110 2
b101001 7
1$
#2860000
0$
#2870000
b101010 7
b100111 2
1$
#2880000
0$
#2890000
b101000 2
b101011 7
1$
#2900000
0$
#2910000
b101100 7
b101001 2
1$
#2920000
0$
#2930000
b101010 2
b101101 7
1$
#2940000
0$
#2950000
b101110 7
b101011 2
1$
#2960000
0$
#2970000
b101100 2
b101111 7
1$
#2980000
0$
#2990000
b110000 7
b101101 2
1$
#3000000
0$
#3010000
b101110 2
b110001 7
1$
#3020000
0$
#3030000
1#
b0 7
b101111 2
1$
#3040000
0$
#3050000
b110000 2
b1 7
1$
#3060000
0$
#3070000
b10 7
b110001 2
1$
#3080000
0$
#3090000
b110010 2
b11 7
1$
#3100000
0$
#3110000
b100 7
b110011 2
1$
#3120000
0$
#3130000
b110100 2
b101 7
1$
#3140000
0$
#3150000
b110 7
b110101 2
1$
#3160000
0$
#3170000
b110110 2
b111 7
1$
#3180000
0$
#3190000
b1000 7
b110111 2
1$
#3200000
0$
#3210000
b111000 2
b1001 7
1$
#3220000
0$
#3230000
b1010 7
b111001 2
1$
#3240000
0$
#3250000
b111010 2
b1011 7
1$
#3260000
0$
#3270000
b1100 7
b111011 2
1$
#3280000
0$
#3290000
b111100 2
b1101 7
1$
#3300000
0$
#3310000
b1110 7
b111101 2
1$
#3320000
0$
#3330000
b111110 2
b1111 7
1$
#3340000
0$
#3350000
b10000 7
b111111 2
1$
#3360000
0$
#3370000
b1000000 2
b10001 7
1$
#3380000
0$
#3390000
b10010 7
b1000001 2
1$
#3400000
0$
#3410000
b1000010 2
b10011 7
1$
#3420000
0$
#3430000
b10100 7
b1000011 2
1$
#3440000
0$
#3450000
b1000100 2
b10101 7
1$
#3460000
0$
#3470000
b10110 7
b1000101 2
1$
#3480000
0$
#3490000
b1000110 2
b10111 7
1$
#3500000
0$
#3510000
b11000 7
b1000111 2
1$
#3520000
0$
#3530000
b1001000 2
b11001 7
1$
#3540000
0$
#3550000
b11010 7
b1001001 2
1$
#3560000
0$
#3570000
b1001010 2
b11011 7
1$
#3580000
0$
#3590000
b11100 7
b1001011 2
1$
#3600000
0$
#3610000
b1001100 2
b11101 7
1$
#3620000
0$
#3630000
b11110 7
b1001101 2
1$
#3640000
0$
#3650000
b1001110 2
b11111 7
1$
#3660000
0$
#3670000
b100000 7
b1001111 2
1$
#3680000
0$
#3690000
b1010000 2
b100001 7
1$
#3700000
0$
#3710000
b100010 7
b1010001 2
1$
#3720000
0$
#3730000
b1010010 2
b100011 7
1$
#3740000
0$
#3750000
b100100 7
b1010011 2
1$
#3760000
0$
#3770000
b1010100 2
b100101 7
1$
#3780000
0$
#3790000
b100110 7
b1010101 2
1$
#3800000
0$
#3810000
b1010110 2
b100111 7
1$
#3820000
0$
#3830000
b101000 7
b1010111 2
1$
#3840000
0$
#3850000
b1011000 2
b101001 7
1$
#3860000
0$
#3870000
b101010 7
b1011001 2
1$
#3880000
0$
#3890000
b1011010 2
b101011 7
1$
#3900000
0$
#3910000
b101100 7
b1011011 2
1$
#3920000
0$
#3930000
b1011100 2
b101101 7
1$
#3940000
0$
#3950000
b101110 7
b1011101 2
1$
#3960000
0$
#3970000
b1011110 2
b101111 7
1$
#3980000
0$
#3990000
b110000 7
b1011111 2
1$
#4000000
0$
#4010000
b1100000 2
b110001 7
1$
#4020000
0$
#4030000
0#
b0 7
b1100001 2
1$
#4040000
0$
#4050000
b1100010 2
b1 7
1$
#4060000
0$
#4070000
b10 7
b1100011 2
1$
#4080000
0$
#4090000
b10 1
1)
b10010100 3
b0 2
b11 7
1$
#4100000
0$
#4110000
b100 7
b1 2
1$
#4120000
0$
#4130000
b10 2
b101 7
1$
#4140000
0$
#4150000
b110 7
b11 2
1$
#4160000
0$
#4170000
b100 2
b111 7
1$
#4180000
0$
#4190000
b1000 7
b101 2
1$
#4200000
0$
#4210000
b110 2
b1001 7
1$
#4220000
0$
#4230000
b1010 7
b111 2
1$
#4240000
0$
#4250000
b1000 2
b1011 7
1$
#4260000
0$
#4270000
b1100 7
b1001 2
1$
#4280000
0$
#4290000
b1010 2
b1101 7
1$
#4300000
0$
#4310000
b1110 7
b1011 2
1$
#4320000
0$
#4330000
b1100 2
b1111 7
1$
#4340000
0$
#4350000
b10000 7
b1101 2
1$
#4360000
0$
#4370000
b1110 2
b10001 7
1$
#4380000
0$
#4390000
b10010 7
b1111 2
1$
#4400000
0$
#4410000
b10000 2
b10011 7
1$
#4420000
0$
#4430000
b10100 7
b10001 2
1$
#4440000
0$
#4450000
b10010 2
b10101 7
1$
#4460000
0$
#4470000
b10110 7
b10011 2
1$
#4480000
0$
#4490000
b10100 2
b10111 7
1$
#4500000
0$
#4510000
b11000 7
b10101 2
1$
#4520000
0$
#4530000
b10110 2
1#
b0 7
1$
#4540000
0$
#4550000
b1 7
b10111 2
1$
#4560000
0$
#4570000
b11000 2
b10 7
1$
#4580000
0$
#4590000
b11 7
b11001 2
1$
#4600000
0$
#4610000
b11010 2
b100 7
1$
#4620000
0$
#4630000
b101 7
b11011 2
1$
#4640000
0$
#4650000
b11100 2
b110 7
1$
#4660000
0$
#4670000
b111 7
b11101 2
1$
#4680000
0$
#4690000
b11110 2
b1000 7
1$
#4700000
0$
#4710000
b1001 7
b11111 2
1$
#4720000
0$
#4730000
b100000 2
b1010 7
1$
#4740000
0$
#4750000
b1011 7
b100001 2
1$
#4760000
0$
#4770000
b100010 2
b1100 7
1$
#4780000
0$
#4790000
b1101 7
b100011 2
1$
#4800000
0$
#4810000
b100100 2
b1110 7
1$
#4820000
0$
#4830000
b1111 7
b100101 2
1$
#4840000
0$
#4850000
b100110 2
b10000 7
1$
#4860000
0$
#4870000
b10001 7
b100111 2
1$
#4880000
0$
#4890000
b101000 2
b10010 7
1$
#4900000
0$
#4910000
b10011 7
b101001 2
1$
#4920000
0$
#4930000
b101010 2
b10100 7
1$
#4940000
0$
#4950000
b10101 7
b101011 2
1$
#4960000
0$
#4970000
b101100 2
b10110 7
1$
#4980000
0$
#4990000
b10111 7
b101101 2
1$
#5000000
0$
#5010000
b101110 2
b11000 7
1$
#5020000
0$
#5030000
0#
b0 7
b101111 2
1$
#5040000
0$
#5050000
b110000 2
b1 7
1$
#5060000
0$
#5070000
b10 7
b110001 2
1$
#5080000
0$
#5090000
b110010 2
b11 7
1$
#5100000
0$
#5110000
b100 7
b110011 2
1$
#5120000
0$
#5130000
b110100 2
b101 7
1$
#5140000
0$
#5150000
b110 7
b110101 2
1$
#5160000
0$
#5170000
b110110 2
b111 7
1$
#5180000
0$
#5190000
b1000 7
b110111 2
1$
#5200000
0$
#5210000
b111000 2
b1001 7
1$
#5220000
0$
#5230000
b1010 7
b111001 2
1$
#5240000
0$
#5250000
b111010 2
b1011 7
1$
#5260000
0$
#5270000
b1100 7
b111011 2
1$
#5280000
0$
#5290000
b111100 2
b1101 7
1$
#5300000
0$
#5310000
b1110 7
b111101 2
1$
#5320000
0$
#5330000
b111110 2
b1111 7
1$
#5340000
0$
#5350000
b10000 7
b111111 2
1$
#5360000
0$
#5370000
b1000000 2
b10001 7
1$
#5380000
0$
#5390000
b10010 7
b1000001 2
1$
#5400000
0$
#5410000
b1000010 2
b10011 7
1$
#5420000
0$
#5430000
b10100 7
b1000011 2
1$
#5440000
0$
#5450000
b1000100 2
b10101 7
1$
#5460000
0$
#5470000
b10110 7
b1000101 2
1$
#5480000
0$
#5490000
b1000110 2
b10111 7
1$
#5500000
0$
#5510000
b11000 7
b1000111 2
1$
#5520000
0$
#5530000
b1001000 2
1#
b0 7
1$
#5540000
0$
#5550000
b1 7
b1001001 2
1$
#5560000
0$
#5570000
b1001010 2
b10 7
1$
#5580000
0$
#5590000
b11 7
b1001011 2
1$
#5600000
0$
#5610000
b1001100 2
b100 7
1$
#5620000
0$
#5630000
b101 7
b1001101 2
1$
#5640000
0$
#5650000
b1001110 2
b110 7
1$
#5660000
0$
#5670000
b111 7
b1001111 2
1$
#5680000
0$
#5690000
b1010000 2
b1000 7
1$
#5700000
0$
#5710000
b1001 7
b1010001 2
1$
#5720000
0$
#5730000
b1010010 2
b1010 7
1$
#5740000
0$
#5750000
b1011 7
b1010011 2
1$
#5760000
0$
#5770000
b1010100 2
b1100 7
1$
#5780000
0$
#5790000
b1101 7
b1010101 2
1$
#5800000
0$
#5810000
b1010110 2
b1110 7
1$
#5820000
0$
#5830000
b1111 7
b1010111 2
1$
#5840000
0$
#5850000
b1011000 2
b10000 7
1$
#5860000
0$
#5870000
b10001 7
b1011001 2
1$
#5880000
0$
#5890000
b1011010 2
b10010 7
1$
#5900000
0$
#5910000
b10011 7
b1011011 2
1$
#5920000
0$
#5930000
b1011100 2
b10100 7
1$
#5940000
0$
#5950000
b10101 7
b1011101 2
1$
#5960000
0$
#5970000
b1011110 2
b10110 7
1$
#5980000
0$
#5990000
b10111 7
b1011111 2
1$
#6000000
0$
#6010000
b1100000 2
b11000 7
1$
#6020000
0$
#6030000
0#
b0 7
b1100001 2
1$
#6040000
0$
#6050000
b1100010 2
b1 7
1$
#6060000
0$
#6070000
b10 7
b1100011 2
1$
#6080000
0$
#6090000
b11 1
0)
b101000 3
b0 2
b11 7
1$
#6100000
0$
#6110000
b100 7
b1 2
1$
#6120000
0$
#6130000
b10 2
b101 7
1$
#6140000
0$
#6150000
b110 7
b11 2
1$
#6160000
0$
#6170000
b100 2
b111 7
1$
#6180000
0$
#6190000
b1000 7
b101 2
1$
#6200000
0$
#6210000
b110 2
b1001 7
1$
#6220000
0$
#6230000
b1010 7
b111 2
1$
#6240000
0$
#6250000
b1000 2
b1011 7
1$
#6260000
0$
#6270000
b1100 7
b1001 2
1$
#6280000
0$
#6290000
b1010 2
b1101 7
1$
#6300000
0$
#6310000
b1110 7
b1011 2
1$
#6320000
0$
#6330000
b1100 2
b1111 7
1$
#6340000
0$
#6350000
b10000 7
b1101 2
1$
#6360000
0$
#6370000
b1110 2
b10001 7
1$
#6380000
0$
#6390000
b10010 7
b1111 2
1$
#6400000
0$
#6410000
b10000 2
b10011 7
1$
#6420000
0$
#6430000
b10100 7
b10001 2
1$
#6440000
0$
#6450000
b10010 2
b10101 7
1$
#6460000
0$
#6470000
b10110 7
b10011 2
1$
